django_no_last_login-0.1.0.dist-info/DESCRIPTION.rst
django_no_last_login-0.1.0.dist-info/METADATA
django_no_last_login-0.1.0.dist-info/RECORD
django_no_last_login-0.1.0.dist-info/WHEEL
django_no_last_login-0.1.0.dist-info/metadata.json
django_no_last_login-0.1.0.dist-info/top_level.txt
nolastlogin/__init__.py
nolastlogin/apps.py
nolastlogin/models.py
